crontip/__init__.py
crontip/__main__.py
crontip/__version__.py
crontip/cli.py
crontip/crontab.py
crontip/file_operate.py
crontip/linux_cmd.py
crontip/backup/backup.bk
crontip/ready/backup.bk
crontip-0.0.3.dist-info/METADATA
crontip-0.0.3.dist-info/WHEEL
crontip-0.0.3.dist-info/entry_points.txt
crontip-0.0.3.dist-info/top_level.txt
crontip-0.0.3.dist-info/RECORD
