Metadata-Version: 2.1
Name: crontip
Version: 0.0.3
Summary: Backup, edit and install crontab
Home-page: https://github.com/shangcode/crontip
Author: shangcode
Author-email: shangcode@aliyun.com
License: CLA
Platform: UNKNOWN
Classifier: Development Status :: 4 - Beta
Classifier: Environment :: Console
Classifier: Operating System :: POSIX :: Linux
Classifier: Programming Language :: Python :: 3
Classifier: Topic :: Software Development :: Libraries :: Python Modules
Classifier: Topic :: System :: Archiving :: Backup
